{
  "costToday": 0.7796,
  "totalCost": 11.2407,
  "totalInputTokens": 801542,
  "totalOutputTokens": 170094,
  "braveSearches": 51,
  "imagesGenerated": 4,
  "lastUpdate": "15:00Z",
  "date": "2026-02-17",
  "breakdown": {
    "miniMax": {
      "inputTokens": 801542,
      "outputTokens": 170094,
      "cost": 0.4446,
      "inputCostPer1k": 0.0003,
      "outputCostPer1k": 0.0012
    },
    "braveSearch": {
      "searches": 51,
      "cost": 0.255,
      "costPerSearch": 0.005
    },
    "geminiImages": {
      "images": 4,
      "cost": 0.08,
      "costPerImage": 0.02
    }
  }
}
